LICENSE.txt
README.rst
setup.cfg
setup.py
ref_type/__init__.py
ref_type.egg-info/PKG-INFO
ref_type.egg-info/SOURCES.txt
ref_type.egg-info/dependency_links.txt
ref_type.egg-info/top_level.txt