Metadata-Version: 2.1
Name: ref-type
Version: 1.0.0
Summary: Referencable objects for Python.
Home-page: https://github.com/xzripper/ref_type
Download-URL: https://github.com/xzripper/time_manager/archive/refs/tags/v1.0.0.tar.gz
Author: Ivan Perzhinsky.
Author-email: name1not1found.com@gmail.com
License: MIT
Keywords: type,reference,utility
Classifier: Development Status :: 5 - Production/Stable 
Classifier: Intended Audience :: Developers
Classifier: Typing :: Typed
Classifier: Topic :: Utilities
Classifier: License :: OSI Approved :: MIT License
Classifier: Programming Language :: Python :: 3
License-File: LICENSE.txt
